emukit/__init__.py
emukit/__version__.py
emukit/bayesian_optimization/__init__.py
emukit/bayesian_optimization/epmgp.py
emukit/bayesian_optimization/local_penalization_calculator.py
emukit/bayesian_optimization/acquisitions/__init__.py
emukit/bayesian_optimization/acquisitions/entropy_search.py
emukit/bayesian_optimization/acquisitions/expected_improvement.py
emukit/bayesian_optimization/acquisitions/local_penalization.py
emukit/bayesian_optimization/acquisitions/log_acquisition.py
emukit/bayesian_optimization/acquisitions/max_value_entropy_search.py
emukit/bayesian_optimization/acquisitions/negative_lower_confidence_bound.py
emukit/bayesian_optimization/acquisitions/probability_of_feasibility.py
emukit/bayesian_optimization/acquisitions/probability_of_improvement.py
emukit/bayesian_optimization/interfaces/__init__.py
emukit/bayesian_optimization/interfaces/models.py
emukit/bayesian_optimization/loops/__init__.py
emukit/bayesian_optimization/loops/bayesian_optimization_loop.py
emukit/bayesian_optimization/loops/cost_sensitive_bayesian_optimization_loop.py
emukit/bayesian_optimization/loops/unknown_constraint_bayesian_optimization_loop.py
emukit/benchmarking/__init__.py
emukit/benchmarking/loop_benchmarking/__init__.py
emukit/benchmarking/loop_benchmarking/benchmark_plot.py
emukit/benchmarking/loop_benchmarking/benchmark_result.py
emukit/benchmarking/loop_benchmarking/benchmarker.py
emukit/benchmarking/loop_benchmarking/metrics.py
emukit/benchmarking/loop_benchmarking/random_search.py
emukit/core/__init__.py
emukit/core/bandit_parameter.py
emukit/core/categorical_parameter.py
emukit/core/constraints.py
emukit/core/continuous_parameter.py
emukit/core/discrete_parameter.py
emukit/core/encodings.py
emukit/core/event_handler.py
emukit/core/parameter.py
emukit/core/parameter_space.py
emukit/core/acquisition/__init__.py
emukit/core/acquisition/acquisition.py
emukit/core/acquisition/acquisition_per_cost.py
emukit/core/acquisition/integrated_acquisition.py
emukit-0.5.0.dist-info/licenses/LICENSE
emukit-0.5.0.dist-info/licenses/NOTICE
emukit-0.5.0.dist-info/METADATA
emukit-0.5.0.dist-info/WHEEL
emukit-0.5.0.dist-info/top_level.txt
emukit-0.5.0.dist-info/RECORD
