Metadata-Version: 2.4
Name: emukit
Version: 0.5.0
Summary: Toolkit for decision making under uncertainty.
Author: Emukit Authors
License: 
Project-URL: Homepage, https://github.com/emukit/emukit
Project-URL: Documentation, https://emukit.readthedocs.io
Project-URL: Source, https://github.com/emukit/emukit
Project-URL: Issues, https://github.com/emukit/emukit/issues
Keywords: bayesian-optimization,active-learning,uncertainty,experimental-design
Classifier: Development Status :: 3 - Alpha
Classifier: Intended Audience :: Developers
Classifier: Intended Audience :: Education
Classifier: Intended Audience :: Science/Research
Classifier: License :: OSI Approved :: Apache Software License
Classifier: Programming Language :: Python :: 3
Classifier: Operating System :: OS Independent
Classifier: Topic :: Scientific/Engineering :: Artificial Intelligence
Classifier: Topic :: Scientific/Engineering :: Mathematics
Classifier: Topic :: Software Development :: Libraries
Classifier: Topic :: Software Development :: Libraries :: Python Modules
Requires-Python: >=3.10
License-File: LICENSE
License-File: NOTICE
Requires-Dist: numpy
Requires-Dist: scipy
Requires-Dist: matplotlib>=3.9
Requires-Dist: emcee>=2.2.1
Requires-Dist: PyDOE>=0.3.0
Requires-Dist: sobol_seq>=0.1.2
Provides-Extra: gpy
Requires-Dist: GPy>=1.13.0; extra == "gpy"
Provides-Extra: bnn
Requires-Dist: pybnn>=0.0.5; extra == "bnn"
Requires-Dist: torch; extra == "bnn"
Provides-Extra: sklearn
Requires-Dist: scikit-learn; extra == "sklearn"
Provides-Extra: examples
Requires-Dist: emukit[bnn,gpy,sklearn]; extra == "examples"
Provides-Extra: docs
Requires-Dist: emukit[gpy]; extra == "docs"
Requires-Dist: ipykernel; extra == "docs"
Requires-Dist: Sphinx>=1.7.5; extra == "docs"
Requires-Dist: nbsphinx>=0.3.4; extra == "docs"
Requires-Dist: sphinx-autodoc-typehints>=1.3.0; extra == "docs"
Requires-Dist: sphinx-rtd-theme>=0.4.1; extra == "docs"
Provides-Extra: tests
Requires-Dist: coverage>=4.5.1; extra == "tests"
Requires-Dist: codecov>=2.0.15; extra == "tests"
Requires-Dist: flake8>=3.5.0; extra == "tests"
Requires-Dist: isort>=5.10; extra == "tests"
Requires-Dist: black; extra == "tests"
Requires-Dist: pytest>=3.5.1; extra == "tests"
Requires-Dist: pytest-cov>=2.5.1; extra == "tests"
Requires-Dist: mock>=2.0.0; extra == "tests"
Provides-Extra: integration-tests
Requires-Dist: emukit[tests]; extra == "integration-tests"
Requires-Dist: pandas; extra == "integration-tests"
Requires-Dist: jupyter; extra == "integration-tests"
Provides-Extra: dev
Requires-Dist: emukit[docs,examples,tests]; extra == "dev"
Dynamic: license-file
